pyconviva/__init__.py
pyconviva/pyconviva.py
pyconviva-0.1.0.dist-info/LICENSE
pyconviva-0.1.0.dist-info/METADATA
pyconviva-0.1.0.dist-info/WHEEL
pyconviva-0.1.0.dist-info/top_level.txt
pyconviva-0.1.0.dist-info/RECORD
