Metadata-Version: 2.2
Name: pyconviva
Version: 0.1.0
Summary: A Python wrapper for Conviva's Metrics V3 API
Author-email: Ben Nour <hello@ben-nour.com>
License: MIT License
Project-URL: homepage, https://github.com/ben-nour/pyconviva
Project-URL: repository, https://github.com/ben-nour/pyconviva
Keywords: conviva,wrapper
Classifier: License :: OSI Approved :: MIT License
Classifier: Programming Language :: Python :: 3
Classifier: Programming Language :: Python :: 3.10
Classifier: Programming Language :: Python :: 3.11
Classifier: Programming Language :: Python :: 3.12
Requires-Python: >=3.10
License-File: LICENSE
Requires-Dist: requests
